vptstools/__init__.py
vptstools/odimh5.py
vptstools/s3.py
vptstools/vpts.py
vptstools/vpts_csv.py
vptstools/bin/click_exception.py
vptstools/bin/transfer_baltrad.py
vptstools/bin/vph5_to_vpts.py
vptstools-0.4.0.dist-info/LICENSE.txt
vptstools-0.4.0.dist-info/METADATA
vptstools-0.4.0.dist-info/WHEEL
vptstools-0.4.0.dist-info/entry_points.txt
vptstools-0.4.0.dist-info/top_level.txt
vptstools-0.4.0.dist-info/RECORD
