Metadata-Version: 2.1
Name: vptstools
Version: 0.4.0
Summary: Tools to work with vertical profile time series.
Home-page: https://enram.github.io/vptstools/
Author: INBO
License: MIT
Project-URL: Documentation, https://enram.github.io/vptstools/
Project-URL: Source, https://github.com/enram/vptstools
Project-URL: Changelog, https://enram.github.io/vptstools/changelog.html
Project-URL: Tracker, https://github.com/enram/vptstools/issues
Platform: any
Classifier: Development Status :: 4 - Beta
Classifier: Programming Language :: Python
Requires-Python: >3.9.0
License-File: LICENSE.txt
Requires-Dist: pandas
Requires-Dist: click
Requires-Dist: h5py >=3.1.0
Requires-Dist: pytz
Requires-Dist: frictionless >=5.3.0
Requires-Dist: importlib-metadata ; python_version < "3.8"
Provides-Extra: develop
Requires-Dist: setuptools ; extra == 'develop'
Requires-Dist: pytest ; extra == 'develop'
Requires-Dist: pytest-cov ; extra == 'develop'
Requires-Dist: flake8 ; extra == 'develop'
Requires-Dist: black ; extra == 'develop'
Requires-Dist: sphinx ; extra == 'develop'
Requires-Dist: sphinx-rtd-theme ; extra == 'develop'
Requires-Dist: sphinx-click ; extra == 'develop'
Requires-Dist: myst-parser[linkify] ; extra == 'develop'
Requires-Dist: moto[s3] <5.0 ; extra == 'develop'
Requires-Dist: tox ; extra == 'develop'
Provides-Extra: transfer
Requires-Dist: s3fs[boto3] ==2023.5.0 ; extra == 'transfer'
Requires-Dist: paramiko ; extra == 'transfer'
Requires-Dist: fsspec ; extra == 'transfer'
Requires-Dist: pyarrow ; extra == 'transfer'
Requires-Dist: python-dotenv ; extra == 'transfer'
